CHANGES
LICENSE
MANIFEST.in
README.rst
quickstart_guide.rst
setup.py
engage_django_sdk/__init__.py
engage_django_sdk/__main__.py
engage_django_sdk/version.py
engage_django_sdk.egg-info/PKG-INFO
engage_django_sdk.egg-info/SOURCES.txt
engage_django_sdk.egg-info/dependency_links.txt
engage_django_sdk.egg-info/entry_points.txt
engage_django_sdk.egg-info/requires.txt
engage_django_sdk.egg-info/top_level.txt
engage_django_sdk/packager/__init__.py
engage_django_sdk/packager/__main__.py
engage_django_sdk/packager/archive_handlers.py
engage_django_sdk/packager/command.py
engage_django_sdk/packager/django_config.py
engage_django_sdk/packager/engage_django_components.py
engage_django_sdk/packager/errors.py
engage_django_sdk/packager/find_module.py
engage_django_sdk/packager/generate_settings.py
engage_django_sdk/packager/json_utils.py
engage_django_sdk/packager/package_data.py
engage_django_sdk/packager/parse_requirements.py
engage_django_sdk/packager/runtests.py
engage_django_sdk/packager/test_find_module.py
engage_django_sdk/packager/test_generate_settings.py
engage_django_sdk/packager/test_parse_requirements.py
engage_django_sdk/packager/test_validation_results.py
engage_django_sdk/packager/utils.py
engage_django_sdk/packager/validation_results.py
refman/Makefile
refman/components.rst
refman/conf.py
refman/debugging.rst
refman/deployment.rst
refman/index.rst
refman/overview.rst
refman/requirements.rst
refman/upgrading.rst
refman/_static/README
refman/_templates/README