Metadata-Version: 1.0
Name: engage-django-sdk
Version: 1.0.0
Summary: Engage SDK for Django
Home-page: http://www.genforma.com
Author: genForma Corporation
Author-email: support@genforma.com
License: Apache V2.0
Platform: UNKNOWN
Classifier: Environment :: Console
Classifier: License :: OSI Approved :: Apache Software License
Classifier: Operating System :: POSIX
Classifier: Topic :: System :: Systems Administration
